be/api/__init__.py
be/api/install.py
be/api/publish.py
fe/static/index.html
app.json
avyas_aurica_base_apps_app_sync-2.2.4.dist-info/METADATA
avyas_aurica_base_apps_app_sync-2.2.4.dist-info/WHEEL
avyas_aurica_base_apps_app_sync-2.2.4.dist-info/RECORD
