Metadata-Version: 2.4
Name: avyas-aurica-base-apps-app-sync
Version: 2.2.4
Summary: Aurica app: app-sync
Requires-Python: >=3.11
Requires-Dist: fastapi>=0.104.0
Requires-Dist: uvicorn>=0.24.0
